pyradigm/__init__.py
pyradigm/__main__.py
pyradigm/_version.py
pyradigm/base.py
pyradigm/classify.py
pyradigm/multiple.py
pyradigm/pyradigm.py
pyradigm/regress.py
pyradigm/utils.py
pyradigm/tests/__init__.py
pyradigm/tests/random_example_dataset.pkl
pyradigm/tests/random_pickled_dataset.pkl
pyradigm/tests/test_BaseDataset_common_behaviours.py
pyradigm/tests/test_MultiDataset.py
pyradigm/tests/test_classify_dataset.py
pyradigm/tests/test_old_pyradigm.py
pyradigm/tests/test_regress_dataset.py
pyradigm/tests/_to_modify/_test_multi_output.py
pyradigm/tests/tmp/ds0.pkl
pyradigm/tests/tmp/ds1.pkl
pyradigm/tests/tmp/ds2.pkl
pyradigm/tests/tmp/ds3.pkl
pyradigm/tests/tmp/ds4.pkl
pyradigm/tests/tmp/ds5.pkl
pyradigm/tests/tmp/ds6.pkl
pyradigm/tests/tmp/ds7.pkl
pyradigm/tests/tmp/random_example_dataset.pkl
pyradigm-0.6.6.dist-info/METADATA
pyradigm-0.6.6.dist-info/WHEEL
pyradigm-0.6.6.dist-info/entry_points.txt
pyradigm-0.6.6.dist-info/licenses/LICENSE.txt
pyradigm-0.6.6.dist-info/RECORD
