Metadata-Version: 2.4
Name: pyradigm
Version: 0.6.6
Summary: Python-based data structure to improve handling of datasets in machine learning workflows
Project-URL: Homepage, https://github.com/raamana/pyradigm
Author-email: Pradeep Reddy Raamana <raamana@gmail.com>
License-Expression: Apache-2.0
License-File: LICENSE.txt
Keywords: data,dataset,learning,machine,provenance,python,structure,test,workflow
Classifier: Intended Audience :: Science/Research
Classifier: Operating System :: MacOS
Classifier: Operating System :: Microsoft :: Windows
Classifier: Operating System :: POSIX
Classifier: Operating System :: Unix
Classifier: Programming Language :: Python
Classifier: Programming Language :: Python :: 3.6
Classifier: Topic :: Scientific/Engineering
Classifier: Topic :: Software Development
Requires-Dist: numpy
Requires-Dist: scipy
Requires-Dist: setuptools
